[
  {
    "id": "n1_00023",
    "word": "お八",
    "reading": "おやつ",
    "meaning": "1. (uk) between meal snack;afternoon refreshment;afternoon tea; 2. mid-day snack",
    "meaningZh": "点心",
    "review": "OK",
    "source_file": "tup_n1\\files\\n1_00023_お八_点心.png",
    "site_image": "assets/images/n1_00023_お八.png"
  },
  {
    "id": "n1_00115",
    "word": "ぶら下げる",
    "reading": "ぶらさげる",
    "meaning": "to hang;to suspend;to dangle;to swing",
    "meaningZh": "悬挂",
    "review": "OK",
    "source_file": "tup_n1\\files\\n1_00115_ぶら下げる_悬挂.png",
    "site_image": "assets/images/n1_00115_ぶら下げる.png"
  },
  {
    "id": "n1_00195",
    "word": "ジャンパー",
    "reading": "ジャンパー / ジャンパ / ジャンバー",
    "meaning": "jacket;jumper",
    "meaningZh": "夹克",
    "review": "OK",
    "source_file": "tup_n1\\files\\n1_00195_ジャンパー_夹克.png",
    "site_image": "assets/images/n1_00195_ジャンパー.png"
  },
  {
    "id": "n1_00209",
    "word": "スポーツカー",
    "reading": "スポーツカー / スポーツ・カー",
    "meaning": "sports car",
    "meaningZh": "跑车",
    "review": "OK",
    "source_file": "tup_n1\\files\\n1_00209_スポーツカー_跑车.png",
    "site_image": "assets/images/n1_00209_スポーツカー.png"
  },
  {
    "id": "n1_00217",
    "word": "ソックス",
    "reading": "ソックス",
    "meaning": "socks",
    "meaningZh": "袜子",
    "review": "OK",
    "source_file": "tup_n1\\files\\n1_00217_ソックス_袜子.png",
    "site_image": "assets/images/n1_00217_ソックス.png"
  },
  {
    "id": "n1_00267",
    "word": "パトカー",
    "reading": "パトカー",
    "meaning": "patrol car",
    "meaningZh": "警车",
    "review": "OK",
    "source_file": "tup_n1\\files\\n1_00267_パトカー_警车.png",
    "site_image": "assets/images/n1_00267_パトカー.png"
  },
  {
    "id": "n1_00311",
    "word": "ユニフォーム",
    "reading": "ユニフォーム / ユニホーム",
    "meaning": "uniform",
    "meaningZh": "制服",
    "review": "OK",
    "source_file": "tup_n1\\files\\n1_00311_ユニフォーム_制服.png",
    "site_image": "assets/images/n1_00311_ユニフォーム.png"
  },
  {
    "id": "n1_00313",
    "word": "ライス",
    "reading": "ライス",
    "meaning": "rice",
    "meaningZh": "米饭",
    "review": "OK",
    "source_file": "tup_n1\\files\\n1_00313_ライス_米饭.png",
    "site_image": "assets/images/n1_00313_ライス.png"
  },
  {
    "id": "n1_00324",
    "word": "レンタカー",
    "reading": "レンタカー",
    "meaning": "hire car (lit: rent-a-car)",
    "meaningZh": "租车",
    "review": "OK",
    "source_file": "tup_n1\\files\\n1_00324_レンタカー_租车.png",
    "site_image": "assets/images/n1_00324_レンタカー.png"
  },
  {
    "id": "n1_00374",
    "word": "三日月",
    "reading": "みかずき",
    "meaning": "new moon;crescent moon",
    "meaningZh": "新月",
    "review": "OK",
    "source_file": "tup_n1\\files\\n1_00374_三日月_新月.png",
    "site_image": "assets/images/n1_00374_三日月.png"
  },
  {
    "id": "n1_00384",
    "word": "上空",
    "reading": "じょうくう",
    "meaning": "sky;the skies;high-altitude sky;upper air",
    "meaningZh": "高空",
    "review": "OK",
    "source_file": "tup_n1\\files\\n1_00384_上空_高空.png",
    "site_image": "assets/images/n1_00384_上空.png"
  },
  {
    "id": "n1_00497",
    "word": "人体",
    "reading": "じんたい",
    "meaning": "human body",
    "meaningZh": "人体",
    "review": "OK",
    "source_file": "tup_n1\\files\\n1_00497_人体_人体.png",
    "site_image": "assets/images/n1_00497_人体.png"
  },
  {
    "id": "n1_00616",
    "word": "使用人",
    "reading": "しようにん",
    "meaning": "employee;servant",
    "meaningZh": "仆人",
    "review": "OK",
    "source_file": "tup_n1\\files\\n1_00616_使用人_仆人.png",
    "site_image": "assets/images/n1_00616_使用人.png"
  },
  {
    "id": "n1_00635",
    "word": "保母",
    "reading": "ほぼ",
    "meaning": "day care worker in a kindergarten nursery school etc.",
    "meaningZh": "保姆",
    "review": "OK",
    "source_file": "tup_n1\\files\\n1_00635_保母_保姆.png",
    "site_image": "assets/images/n1_00635_保母.png"
  },
  {
    "id": "n1_01089",
    "word": "吹奏",
    "reading": "すいそう",
    "meaning": "playing wind instruments",
    "meaningZh": "吹奏",
    "review": "OK",
    "source_file": "tup_n1\\files\\n1_01089_吹奏_吹奏.png",
    "site_image": "assets/images/n1_01089_吹奏.png"
  },
  {
    "id": "n1_01129",
    "word": "喫茶",
    "reading": "きっさ",
    "meaning": "tea drinking;tea house",
    "meaningZh": "茶馆",
    "review": "OK",
    "source_file": "tup_n1\\files\\n1_01129_喫茶_茶馆.png",
    "site_image": "assets/images/n1_01129_喫茶.png"
  },
  {
    "id": "n1_01362",
    "word": "富豪",
    "reading": "ふごう",
    "meaning": "wealthy person;millionaire",
    "meaningZh": "富豪",
    "review": "OK",
    "source_file": "tup_n1\\files\\n1_01362_富豪_富豪.png",
    "site_image": "assets/images/n1_01362_富豪.png"
  },
  {
    "id": "n1_01420",
    "word": "山脈",
    "reading": "さんみゃく",
    "meaning": "mountain range",
    "meaningZh": "山脉",
    "review": "OK",
    "source_file": "tup_n1\\files\\n1_01420_山脈_山脉.png",
    "site_image": "assets/images/n1_01420_山脈.png"
  },
  {
    "id": "n1_01463",
    "word": "年輪",
    "reading": "ねんりん",
    "meaning": "annual tree ring",
    "meaningZh": "年轮",
    "review": "OK",
    "source_file": "tup_n1\\files\\n1_01463_年輪_年轮.png",
    "site_image": "assets/images/n1_01463_年輪.png"
  },
  {
    "id": "n1_01506",
    "word": "弟",
    "reading": "おと",
    "meaning": "younger brother",
    "meaningZh": "弟弟",
    "review": "OK",
    "source_file": "tup_n1\\files\\n1_01506_弟_弟弟.png",
    "site_image": "assets/images/n1_01506_弟.png"
  },
  {
    "id": "n1_01950",
    "word": "晴天",
    "reading": "せいてん",
    "meaning": "fine weather",
    "meaningZh": "晴天",
    "review": "OK",
    "source_file": "tup_n1\\files\\n1_01950_晴天_晴天.png",
    "site_image": "assets/images/n1_01950_晴天.png"
  },
  {
    "id": "n1_02016",
    "word": "杯",
    "reading": "さかずき",
    "meaning": "wine cups",
    "meaningZh": "酒杯",
    "review": "OK",
    "source_file": "tup_n1\\files\\n1_02016_杯_酒杯.png",
    "site_image": "assets/images/n1_02016_杯.png"
  },
  {
    "id": "n1_02312",
    "word": "焚火",
    "reading": "たきび",
    "meaning": "(open) fire",
    "meaningZh": "篝火",
    "review": "OK",
    "source_file": "tup_n1\\files\\n1_02312_焚火_篝火.png",
    "site_image": "assets/images/n1_02312_焚火.png"
  },
  {
    "id": "n1_02349",
    "word": "熱湯",
    "reading": "ねっとう",
    "meaning": "boiling water",
    "meaningZh": "沸水",
    "review": "OK",
    "source_file": "tup_n1\\files\\n1_02349_熱湯_沸水.png",
    "site_image": "assets/images/n1_02349_熱湯.png"
  },
  {
    "id": "n1_02816",
    "word": "船舶",
    "reading": "せんぱく",
    "meaning": "ship",
    "meaningZh": "船舶",
    "review": "OK",
    "source_file": "tup_n1\\files\\n1_02816_船舶_船舶.png",
    "site_image": "assets/images/n1_02816_船舶.png"
  },
  {
    "id": "n1_02827",
    "word": "花壇",
    "reading": "かだん",
    "meaning": "flower bed",
    "meaningZh": "花坛",
    "review": "OK",
    "source_file": "tup_n1\\files\\n1_02827_花壇_花坛.png",
    "site_image": "assets/images/n1_02827_花壇.png"
  },
  {
    "id": "n1_02829",
    "word": "苗",
    "reading": "なえ",
    "meaning": "rice seedling",
    "meaningZh": "秧苗",
    "review": "OK",
    "source_file": "tup_n1\\files\\n1_02829_苗_秧苗.png",
    "site_image": "assets/images/n1_02829_苗.png"
  },
  {
    "id": "n1_03135",
    "word": "軍服",
    "reading": "ぐんぷく",
    "meaning": "military or naval uniform",
    "meaningZh": "军服",
    "review": "OK",
    "source_file": "tup_n1\\files\\n1_03135_軍服_军服.png",
    "site_image": "assets/images/n1_03135_軍服.png"
  },
  {
    "id": "n1_03362",
    "word": "雛",
    "reading": "ひな",
    "meaning": "young bird;chick;doll",
    "meaningZh": "雏鸟;玩偶",
    "review": "OK",
    "source_file": "tup_n1\\files\\n1_03362_雛_雏鸟;玩偶.png",
    "site_image": "assets/images/n1_03362_雛.png"
  },
  {
    "id": "n1_03365",
    "word": "雨具",
    "reading": "あまぐ",
    "meaning": "rain gear",
    "meaningZh": "雨衣",
    "review": "OK",
    "source_file": "tup_n1\\files\\n1_03365_雨具_雨衣.png",
    "site_image": "assets/images/n1_03365_雨具.png"
  },
  {
    "id": "n1_03366",
    "word": "雨天",
    "reading": "うてん",
    "meaning": "rainy weather",
    "meaningZh": "下雨天",
    "review": "OK",
    "source_file": "tup_n1\\files\\n1_03366_雨天_下雨天.png",
    "site_image": "assets/images/n1_03366_雨天.png"
  },
  {
    "id": "n2_03510",
    "word": "おやつ",
    "reading": "おやつ",
    "meaning": "(1) between meal snack,afternoon refreshment",
    "meaningZh": "点心",
    "review": "OK",
    "source_file": "tup_n2\\files\\n2_03510_おやつ_点心.png",
    "site_image": "assets/images/n2_03510_おやつ.png"
  },
  {
    "id": "n2_03553",
    "word": "しびれる",
    "reading": "しびれる / シビれる / シビレる",
    "meaning": "to become numb,to go to sleep (i.e., a limb)",
    "meaningZh": "麻木；入睡",
    "review": "OK",
    "source_file": "tup_n2\\files\\n2_03553_しびれる_麻木；入睡.png",
    "site_image": "assets/images/n2_03553_しびれる.png"
  },
  {
    "id": "n2_03556",
    "word": "しゃがむ",
    "reading": "しゃがむ",
    "meaning": "to squat",
    "meaningZh": "蹲下",
    "review": "OK",
    "source_file": "tup_n2\\files\\n2_03556_しゃがむ_蹲下.png",
    "site_image": "assets/images/n2_03556_しゃがむ.png"
  },
  {
    "id": "n2_03617",
    "word": "ぺん",
    "reading": "",
    "meaning": "pen",
    "meaningZh": "笔",
    "review": "OK",
    "source_file": "tup_n2\\files\\n2_03617_ぺん_笔.png",
    "site_image": "assets/images/n2_03617_ぺん.png"
  },
  {
    "id": "n2_03804",
    "word": "並木",
    "reading": "なみき",
    "meaning": "roadside tree,row of trees",
    "meaningZh": "行道树；树列",
    "review": "OK",
    "source_file": "tup_n2\\files\\n2_03804_並木_行道树；树列.png",
    "site_image": "assets/images/n2_03804_並木.png"
  },
  {
    "id": "n2_03828",
    "word": "井戸",
    "reading": "いど",
    "meaning": "water well",
    "meaningZh": "水井",
    "review": "OK",
    "source_file": "tup_n2\\files\\n2_03828_井戸_水井.png",
    "site_image": "assets/images/n2_03828_井戸.png"
  },
  {
    "id": "n2_03887",
    "word": "便箋",
    "reading": "びんせん",
    "meaning": "writing paper,stationery",
    "meaningZh": "便笺",
    "review": "OK",
    "source_file": "tup_n2\\files\\n2_03887_便箋_便笺.png",
    "site_image": "assets/images/n2_03887_便箋.png"
  },
  {
    "id": "n2_03984",
    "word": "刺身",
    "reading": "さしみ",
    "meaning": "sliced raw fish",
    "meaningZh": "生鱼片",
    "review": "OK",
    "source_file": "tup_n2\\files\\n2_03984_刺身_生鱼片.png",
    "site_image": "assets/images/n2_03984_刺身.png"
  },
  {
    "id": "n2_04018",
    "word": "匙",
    "reading": "さじ",
    "meaning": "spoon",
    "meaningZh": "勺子",
    "review": "OK",
    "source_file": "tup_n2\\files\\n2_04018_匙_勺子.png",
    "site_image": "assets/images/n2_04018_匙.png"
  },
  {
    "id": "n2_04069",
    "word": "吊る",
    "reading": "つる",
    "meaning": "to hang",
    "meaningZh": "悬挂",
    "review": "OK",
    "source_file": "tup_n2\\files\\n2_04069_吊る_悬挂.png",
    "site_image": "assets/images/n2_04069_吊る.png"
  },
  {
    "id": "n2_04080",
    "word": "吹雪",
    "reading": "ふぶき",
    "meaning": "snow storm",
    "meaningZh": "暴风雪",
    "review": "OK",
    "source_file": "tup_n2\\files\\n2_04080_吹雪_暴风雪.png",
    "site_image": "assets/images/n2_04080_吹雪.png"
  },
  {
    "id": "n2_04087",
    "word": "和服",
    "reading": "わふく",
    "meaning": "Japanese clothes",
    "meaningZh": "和服",
    "review": "OK",
    "source_file": "tup_n2\\files\\n2_04087_和服_和服.png",
    "site_image": "assets/images/n2_04087_和服.png"
  },
  {
    "id": "n2_04091",
    "word": "商店",
    "reading": "しょうてん",
    "meaning": "shop,business firm",
    "meaningZh": "商店",
    "review": "OK",
    "source_file": "tup_n2\\files\\n2_04091_商店_商店.png",
    "site_image": "assets/images/n2_04091_商店.png"
  },
  {
    "id": "n2_04099",
    "word": "噴水",
    "reading": "ふんすい",
    "meaning": "water fountain",
    "meaningZh": "喷泉",
    "review": "OK",
    "source_file": "tup_n2\\files\\n2_04099_噴水_喷泉.png",
    "site_image": "assets/images/n2_04099_噴水.png"
  },
  {
    "id": "n2_04150",
    "word": "塵紙",
    "reading": "ちりがみ",
    "meaning": "tissue paper,toilet paper",
    "meaningZh": "纸巾; 卫生纸",
    "review": "OK",
    "source_file": "tup_n2\\files\\n2_04150_塵紙_纸巾;_卫生纸.png",
    "site_image": "assets/images/n2_04150_塵紙.png"
  },
  {
    "id": "n2_04164",
    "word": "夕日",
    "reading": "ゆうひ",
    "meaning": "(in) the evening sun,setting sun",
    "meaningZh": "夕阳",
    "review": "OK",
    "source_file": "tup_n2\\files\\n2_04164_夕日_夕阳.png",
    "site_image": "assets/images/n2_04164_夕日.png"
  },
  {
    "id": "n2_04178",
    "word": "大木",
    "reading": "たいぼく",
    "meaning": "large tree",
    "meaningZh": "大树",
    "review": "OK",
    "source_file": "tup_n2\\files\\n2_04178_大木_大树.png",
    "site_image": "assets/images/n2_04178_大木.png"
  },
  {
    "id": "n2_04184",
    "word": "女の人",
    "reading": "おんなのひと",
    "meaning": "woman",
    "meaningZh": "女士",
    "review": "OK",
    "source_file": "tup_n2\\files\\n2_04184_女の人_女士.png",
    "site_image": "assets/images/n2_04184_女の人.png"
  },
  {
    "id": "n2_04259",
    "word": "山林",
    "reading": "さんりん",
    "meaning": "mountain forest,mountains and forest",
    "meaningZh": "山林；山地森林；林区",
    "review": "OK",
    "source_file": "tup_n2\\files\\n2_04259_山林_山林；山地森林；林区.png",
    "site_image": "assets/images/n2_04259_山林.png"
  },
  {
    "id": "n2_04491",
    "word": "日当たり",
    "reading": "ひあたり",
    "meaning": "exposure to the sun,sunny place",
    "meaningZh": "向阳地；阳光充足处",
    "review": "OK",
    "source_file": "tup_n2\\files\\n2_04491_日当たり_向阳地；阳光充足处.png",
    "site_image": "assets/images/n2_04491_日当たり.png"
  },
  {
    "id": "n2_04517",
    "word": "書籍",
    "reading": "しょせき",
    "meaning": "book,publication",
    "meaningZh": "书",
    "review": "OK",
    "source_file": "tup_n2\\files\\n2_04517_書籍_书.png",
    "site_image": "assets/images/n2_04517_書籍.png"
  },
  {
    "id": "n2_04541",
    "word": "果実",
    "reading": "かじつ",
    "meaning": "fruit,nut,berry.",
    "meaningZh": "水果",
    "review": "OK",
    "source_file": "tup_n2\\files\\n2_04541_果実_水果.png",
    "site_image": "assets/images/n2_04541_果実.png"
  },
  {
    "id": "n2_04597",
    "word": "水滴",
    "reading": "すいてき",
    "meaning": "drop of water",
    "meaningZh": "水滴",
    "review": "OK",
    "source_file": "tup_n2\\files\\n2_04597_水滴_水滴.png",
    "site_image": "assets/images/n2_04597_水滴.png"
  },
  {
    "id": "n2_04627",
    "word": "海洋",
    "reading": "かいよう",
    "meaning": "ocean",
    "meaningZh": "海洋；大海",
    "review": "OK",
    "source_file": "tup_n2\\files\\n2_04627_海洋_海洋；大海.png",
    "site_image": "assets/images/n2_04627_海洋.png"
  },
  {
    "id": "n2_04633",
    "word": "消防署",
    "reading": "しょうぼうしょ",
    "meaning": "fire station",
    "meaningZh": "消防站",
    "review": "OK",
    "source_file": "tup_n2\\files\\n2_04633_消防署_消防站.png",
    "site_image": "assets/images/n2_04633_消防署.png"
  },
  {
    "id": "n2_04732",
    "word": "物置",
    "reading": "ものおき",
    "meaning": "storage room",
    "meaningZh": "储物间",
    "review": "OK",
    "source_file": "tup_n2\\files\\n2_04732_物置_储物间.png",
    "site_image": "assets/images/n2_04732_物置.png"
  },
  {
    "id": "n2_04755",
    "word": "生け花",
    "reading": "いけばな",
    "meaning": "(1) flower arrangement",
    "meaningZh": "花艺",
    "review": "OK",
    "source_file": "tup_n2\\files\\n2_04755_生け花_花艺.png",
    "site_image": "assets/images/n2_04755_生け花.png"
  },
  {
    "id": "n2_04766",
    "word": "田植え",
    "reading": "たうえ",
    "meaning": "rice planting",
    "meaningZh": "插秧",
    "review": "OK",
    "source_file": "tup_n2\\files\\n2_04766_田植え_插秧.png",
    "site_image": "assets/images/n2_04766_田植え.png"
  },
  {
    "id": "n2_04865",
    "word": "窓口",
    "reading": "まどぐち",
    "meaning": "ticket window",
    "meaningZh": "窗口",
    "review": "OK",
    "source_file": "tup_n2\\files\\n2_04865_窓口_窗口.png",
    "site_image": "assets/images/n2_04865_窓口.png"
  },
  {
    "id": "n2_04868",
    "word": "競馬",
    "reading": "けいば",
    "meaning": "horse racing",
    "meaningZh": "赛马",
    "review": "OK",
    "source_file": "tup_n2\\files\\n2_04868_競馬_赛马.png",
    "site_image": "assets/images/n2_04868_競馬.png"
  },
  {
    "id": "n2_04887",
    "word": "紙幣",
    "reading": "しへい",
    "meaning": "paper money,notes,bills",
    "meaningZh": "纸币",
    "review": "OK",
    "source_file": "tup_n2\\files\\n2_04887_紙幣_纸币.png",
    "site_image": "assets/images/n2_04887_紙幣.png"
  },
  {
    "id": "n2_04950",
    "word": "腰掛ける",
    "reading": "こしかける",
    "meaning": "to sit (down)",
    "meaningZh": "坐下",
    "review": "OK",
    "source_file": "tup_n2\\files\\n2_04950_腰掛ける_坐下.png",
    "site_image": "assets/images/n2_04950_腰掛ける.png"
  },
  {
    "id": "n2_04972",
    "word": "茶碗",
    "reading": "ちゃわん",
    "meaning": "rice bowl,tea cup,teacup",
    "meaningZh": "饭碗",
    "review": "OK",
    "source_file": "tup_n2\\files\\n2_04972_茶碗_饭碗.png",
    "site_image": "assets/images/n2_04972_茶碗.png"
  },
  {
    "id": "n2_04991",
    "word": "薬品",
    "reading": "やくひん",
    "meaning": "medicine(s),chemical(s)",
    "meaningZh": "药品",
    "review": "OK",
    "source_file": "tup_n2\\files\\n2_04991_薬品_药品.png",
    "site_image": "assets/images/n2_04991_薬品.png"
  },
  {
    "id": "n2_05090",
    "word": "跳ぶ",
    "reading": "とぶ",
    "meaning": "to jump,to fly,to leap",
    "meaningZh": "跳跃",
    "review": "OK",
    "source_file": "tup_n2\\files\\n2_05090_跳ぶ_跳跃.png",
    "site_image": "assets/images/n2_05090_跳ぶ.png"
  },
  {
    "id": "n2_05143",
    "word": "遊園地",
    "reading": "ゆうえんち",
    "meaning": "amusement park",
    "meaningZh": "游乐园",
    "review": "OK",
    "source_file": "tup_n2\\files\\n2_05143_遊園地_游乐园.png",
    "site_image": "assets/images/n2_05143_遊園地.png"
  },
  {
    "id": "n2_05228",
    "word": "電柱",
    "reading": "でんちゅう",
    "meaning": "telephone pole,telegraph pole,lightpole",
    "meaningZh": "电线杆",
    "review": "OK",
    "source_file": "tup_n2\\files\\n2_05228_電柱_电线杆.png",
    "site_image": "assets/images/n2_05228_電柱.png"
  },
  {
    "id": "n2_05256",
    "word": "食塩",
    "reading": "しょくえん",
    "meaning": "table salt",
    "meaningZh": "食盐",
    "review": "OK",
    "source_file": "tup_n2\\files\\n2_05256_食塩_食盐.png",
    "site_image": "assets/images/n2_05256_食塩.png"
  },
  {
    "id": "n3_05306",
    "word": "おじいさん",
    "reading": "おじいさん",
    "meaning": "grandfather,male senior-citizen",
    "meaningZh": "祖父、爷爷",
    "review": "OK",
    "source_file": "tup_n3\\files\\n3_05306_おじいさん_祖父、爷爷.png",
    "site_image": "assets/images/n3_05306_おじいさん.png"
  },
  {
    "id": "n3_05314",
    "word": "お目に掛かる",
    "reading": "おめにかかる",
    "meaning": "to meet (someone of higher status) | to be recognized (esp. by someone of higher status) | to be visible",
    "meaningZh": "拜见、被看见",
    "review": "OK",
    "source_file": "tup_n3\\files\\n3_05314_お目に掛かる_拜见、被看见.png",
    "site_image": "assets/images/n3_05314_お目に掛かる.png"
  },
  {
    "id": "n3_05315",
    "word": "お腹",
    "reading": "おなか",
    "meaning": "stomach",
    "meaningZh": "肚子、胃",
    "review": "OK",
    "source_file": "tup_n3\\files\\n3_05315_お腹_肚子、胃.png",
    "site_image": "assets/images/n3_05315_お腹.png"
  },
  {
    "id": "n3_05355",
    "word": "そっと",
    "reading": "そっと / そうっと / そおっと",
    "meaning": "face of the earth",
    "meaningZh": "地面、地表",
    "review": "OK",
    "source_file": "tup_n3\\files\\n3_05355_そっと_地面、地表.png",
    "site_image": "assets/images/n3_05355_そっと.png"
  },
  {
    "id": "n3_05434",
    "word": "カー",
    "reading": "カー",
    "meaning": "car",
    "meaningZh": "汽车",
    "review": "OK",
    "source_file": "tup_n3\\files\\n3_05434_カー_汽车.png",
    "site_image": "assets/images/n3_05434_カー.png"
  },
  {
    "id": "n3_05442",
    "word": "グラス",
    "reading": "グラス",
    "meaning": "(1) glass,(2) grass",
    "meaningZh": "玻璃杯、草",
    "review": "OK",
    "source_file": "tup_n3\\files\\n3_05442_グラス_玻璃杯、草.png",
    "site_image": "assets/images/n3_05442_グラス.png"
  },
  {
    "id": "n3_05448",
    "word": "コンピューター",
    "reading": "コンピュータ / コンピューター",
    "meaning": "computer",
    "meaningZh": "电脑、计算机",
    "review": "OK",
    "source_file": "tup_n3\\files\\n3_05448_コンピューター_电脑、计算机.png",
    "site_image": "assets/images/n3_05448_コンピューター.png"
  },
  {
    "id": "n3_05464",
    "word": "スープ",
    "reading": "スープ",
    "meaning": "(Western) soup",
    "meaningZh": "汤、西式汤",
    "review": "OK",
    "source_file": "tup_n3\\files\\n3_05464_スープ_汤、西式汤.png",
    "site_image": "assets/images/n3_05464_スープ.png"
  },
  {
    "id": "n3_05484",
    "word": "ドレス",
    "reading": "ドレス",
    "meaning": "dress",
    "meaningZh": "连衣裙、礼服",
    "review": "OK",
    "source_file": "tup_n3\\files\\n3_05484_ドレス_连衣裙、礼服.png",
    "site_image": "assets/images/n3_05484_ドレス.png"
  },
  {
    "id": "n3_05498",
    "word": "ビール",
    "reading": "ばくしゅ / ビール",
    "meaning": "beer",
    "meaningZh": "啤酒",
    "review": "OK",
    "source_file": "tup_n3\\files\\n3_05498_ビール_啤酒.png",
    "site_image": "assets/images/n3_05498_ビール.png"
  },
  {
    "id": "n3_05505",
    "word": "ベルト",
    "reading": "ベルト",
    "meaning": "Belt for western clothes",
    "meaningZh": "皮带、腰带",
    "review": "OK",
    "source_file": "tup_n3\\files\\n3_05505_ベルト_皮带、腰带.png",
    "site_image": "assets/images/n3_05505_ベルト.png"
  },
  {
    "id": "n3_05517",
    "word": "ミルク",
    "reading": "ミルク",
    "meaning": "milk",
    "meaningZh": "牛奶",
    "review": "OK",
    "source_file": "tup_n3\\files\\n3_05517_ミルク_牛奶.png",
    "site_image": "assets/images/n3_05517_ミルク.png"
  },
  {
    "id": "n3_05527",
    "word": "ワイン",
    "reading": "ワイン",
    "meaning": "wine",
    "meaningZh": "葡萄酒、红酒",
    "review": "OK",
    "source_file": "tup_n3\\files\\n3_05527_ワイン_葡萄酒、红酒.png",
    "site_image": "assets/images/n3_05527_ワイン.png"
  },
  {
    "id": "n3_05606",
    "word": "人込み",
    "reading": "ひとごみ",
    "meaning": "crowd of people",
    "meaningZh": "人群",
    "review": "OK",
    "source_file": "tup_n3\\files\\n3_05606_人込み_人群.png",
    "site_image": "assets/images/n3_05606_人込み.png"
  },
  {
    "id": "n3_05685",
    "word": "停留所",
    "reading": "ていりゅうじょ",
    "meaning": "bus or tram stop",
    "meaningZh": "公交站、电车站",
    "review": "OK",
    "source_file": "tup_n3\\files\\n3_05685_停留所_公交站、电车站.png",
    "site_image": "assets/images/n3_05685_停留所.png"
  },
  {
    "id": "n3_05705",
    "word": "兎",
    "reading": "うさぎ",
    "meaning": "rabbit,hare,cony",
    "meaningZh": "兔子",
    "review": "OK",
    "source_file": "tup_n3\\files\\n3_05705_兎_兔子.png",
    "site_image": "assets/images/n3_05705_兎.png"
  },
  {
    "id": "n3_05750",
    "word": "列車",
    "reading": "れっしゃ",
    "meaning": "train (ordinary)",
    "meaningZh": "列车、火车",
    "review": "OK",
    "source_file": "tup_n3\\files\\n3_05750_列車_列车、火车.png",
    "site_image": "assets/images/n3_05750_列車.png"
  },
  {
    "id": "n3_05793",
    "word": "医師",
    "reading": "いし",
    "meaning": "doctor,physician",
    "meaningZh": "医生",
    "review": "OK",
    "source_file": "tup_n3\\files\\n3_05793_医師_医生.png",
    "site_image": "assets/images/n3_05793_医師.png"
  },
  {
    "id": "n3_05951",
    "word": "太陽",
    "reading": "たいよう",
    "meaning": "sun,solar",
    "meaningZh": "太阳",
    "review": "OK",
    "source_file": "tup_n3\\files\\n3_05951_太陽_太阳.png",
    "site_image": "assets/images/n3_05951_太陽.png"
  },
  {
    "id": "n3_05963",
    "word": "女子",
    "reading": "じょし",
    "meaning": "woman,girl",
    "meaningZh": "女孩",
    "review": "OK",
    "source_file": "tup_n3\\files\\n3_05963_女子_女孩.png",
    "site_image": "assets/images/n3_05963_女子.png"
  },
  {
    "id": "n3_06037",
    "word": "居間",
    "reading": "いま",
    "meaning": "living room (western style)",
    "meaningZh": "客厅",
    "review": "OK",
    "source_file": "tup_n3\\files\\n3_06037_居間_客厅.png",
    "site_image": "assets/images/n3_06037_居間.png"
  },
  {
    "id": "n3_06040",
    "word": "履く",
    "reading": "はく",
    "meaning": "to wear,to put on (lower body)",
    "meaningZh": "穿下装、穿鞋",
    "review": "OK",
    "source_file": "tup_n3\\files\\n3_06040_履く_穿下装、穿鞋.png",
    "site_image": "assets/images/n3_06040_履く.png"
  },
  {
    "id": "n3_06087",
    "word": "弁当",
    "reading": "べんとう",
    "meaning": "box lunch",
    "meaningZh": "便当",
    "review": "OK",
    "source_file": "tup_n3\\files\\n3_06087_弁当_便当.png",
    "site_image": "assets/images/n3_06087_弁当.png"
  },
  {
    "id": "n3_06176",
    "word": "戦う",
    "reading": "たたかう",
    "meaning": "to fight,to battle,to combat",
    "meaningZh": "战斗、打仗",
    "review": "OK",
    "source_file": "tup_n3\\files\\n3_06176_戦う_战斗、打仗.png",
    "site_image": "assets/images/n3_06176_戦う.png"
  },
  {
    "id": "n3_06196",
    "word": "抱く",
    "reading": "いだく",
    "meaning": "(sl) to embrace,to hug,to harbour,to entertain",
    "meaningZh": "抱、拥抱、怀有",
    "review": "OK",
    "source_file": "tup_n3\\files\\n3_06196_抱く_抱、拥抱、怀有.png",
    "site_image": "assets/images/n3_06196_抱く.png"
  },
  {
    "id": "n3_06242",
    "word": "教師",
    "reading": "きょうし",
    "meaning": "teacher (classroom)",
    "meaningZh": "教师、老师",
    "review": "OK",
    "source_file": "tup_n3\\files\\n3_06242_教師_教师、老师.png",
    "site_image": "assets/images/n3_06242_教師.png"
  },
  {
    "id": "n3_06244",
    "word": "教科書",
    "reading": "きょうかしょ",
    "meaning": "text book",
    "meaningZh": "教科书",
    "review": "OK",
    "source_file": "tup_n3\\files\\n3_06244_教科書_教科书.png",
    "site_image": "assets/images/n3_06244_教科書.png"
  },
  {
    "id": "n3_06306",
    "word": "月",
    "reading": "つき",
    "meaning": "moon,month",
    "meaningZh": "月亮",
    "review": "OK",
    "source_file": "tup_n3\\files\\n3_06306_月_月亮.png",
    "site_image": "assets/images/n3_06306_月.png"
  },
  {
    "id": "n3_06329",
    "word": "松",
    "reading": "まつ",
    "meaning": "(1) pine tree,(2) highest (of a three-tier ranking system)",
    "meaningZh": "松树、最高级",
    "review": "OK",
    "source_file": "tup_n3\\files\\n3_06329_松_松树、最高级.png",
    "site_image": "assets/images/n3_06329_松.png"
  },
  {
    "id": "n3_06342",
    "word": "椅子",
    "reading": "いす",
    "meaning": "chair",
    "meaningZh": "椅子",
    "review": "OK",
    "source_file": "tup_n3\\files\\n3_06342_椅子_椅子.png",
    "site_image": "assets/images/n3_06342_椅子.png"
  },
  {
    "id": "n3_06358",
    "word": "機械",
    "reading": "きかい",
    "meaning": "machine,mechanism",
    "meaningZh": "机器、机械",
    "review": "OK",
    "source_file": "tup_n3\\files\\n3_06358_機械_机器、机械.png",
    "site_image": "assets/images/n3_06358_機械.png"
  },
  {
    "id": "n3_06520",
    "word": "田",
    "reading": "た",
    "meaning": "rice field",
    "meaningZh": "稻田",
    "review": "OK",
    "source_file": "tup_n3\\files\\n3_06520_田_稻田.png",
    "site_image": "assets/images/n3_06520_田.png"
  },
  {
    "id": "n3_06718",
    "word": "船",
    "reading": "ふね",
    "meaning": "ship,boat,watercraft,shipping,vessel,steamship",
    "meaningZh": "船",
    "review": "OK",
    "source_file": "tup_n3\\files\\n3_06718_船_船.png",
    "site_image": "assets/images/n3_06718_船.png"
  },
  {
    "id": "n3_06732",
    "word": "虎",
    "reading": "とら",
    "meaning": "tiger",
    "meaningZh": "老虎",
    "review": "OK",
    "source_file": "tup_n3\\files\\n3_06732_虎_老虎.png",
    "site_image": "assets/images/n3_06732_虎.png"
  },
  {
    "id": "n3_07054",
    "word": "馬",
    "reading": "うま",
    "meaning": "(1) horse,(2) promoted bishop (shogi)",
    "meaningZh": "马",
    "review": "OK",
    "source_file": "tup_n3\\files\\n3_07054_馬_马.png",
    "site_image": "assets/images/n3_07054_馬.png"
  },
  {
    "id": "n3_07067",
    "word": "魚",
    "reading": "うお",
    "meaning": "fish",
    "meaningZh": "鱼",
    "review": "OK",
    "source_file": "tup_n3\\files\\n3_07067_魚_鱼.png",
    "site_image": "assets/images/n3_07067_魚.png"
  },
  {
    "id": "n3_07070",
    "word": "鼠",
    "reading": "ねずみ",
    "meaning": "(1) mouse,rat,(2) dark gray,slate color",
    "meaningZh": "老鼠、深灰色",
    "review": "OK",
    "source_file": "tup_n3\\files\\n3_07070_鼠_老鼠、深灰色.png",
    "site_image": "assets/images/n3_07070_鼠.png"
  },
  {
    "id": "n4_07093",
    "word": "お・金持ち",
    "reading": "かねもち/おかねもち",
    "meaning": "rich man",
    "meaningZh": "有钱人",
    "review": "OK",
    "source_file": "tup_n4\\files\\n4_07093_お・金持ち_有钱人.png",
    "site_image": "assets/images/n4_07093_お_金持ち.png"
  },
  {
    "id": "n4_07147",
    "word": "つき",
    "reading": "つくえ / つき",
    "meaning": "moon",
    "meaningZh": "月亮",
    "review": "OK",
    "source_file": "tup_n4\\files\\n4_07147_つき_月亮.png",
    "site_image": "assets/images/n4_07147_つき.png"
  },
  {
    "id": "n4_07193",
    "word": "ガソリンスタンド",
    "reading": "ガソリンスタンド / ガソリン・スタンド",
    "meaning": "petrol station",
    "meaningZh": "加油站",
    "review": "OK",
    "source_file": "tup_n4\\files\\n4_07193_ガソリンスタンド_加油站.png",
    "site_image": "assets/images/n4_07193_ガソリンスタンド.png"
  },
  {
    "id": "n4_07194",
    "word": "ガラス",
    "reading": "ガラス",
    "meaning": "a glass pane",
    "meaningZh": "玻璃、玻璃窗",
    "review": "OK",
    "source_file": "tup_n4\\files\\n4_07194_ガラス_玻璃、玻璃窗.png",
    "site_image": "assets/images/n4_07194_ガラス.png"
  },
  {
    "id": "n4_07195",
    "word": "ケーキ",
    "reading": "ケーキ",
    "meaning": "cake",
    "meaningZh": "蛋糕",
    "review": "OK",
    "source_file": "tup_n4\\files\\n4_07195_ケーキ_蛋糕.png",
    "site_image": "assets/images/n4_07195_ケーキ.png"
  },
  {
    "id": "n4_07213",
    "word": "パソコン",
    "reading": "パソコン",
    "meaning": "personal computer",
    "meaningZh": "个人电脑",
    "review": "OK",
    "source_file": "tup_n4\\files\\n4_07213_パソコン_个人电脑.png",
    "site_image": "assets/images/n4_07213_パソコン.png"
  },
  {
    "id": "n4_07215",
    "word": "ビル",
    "reading": "ビル",
    "meaning": "building or bill",
    "meaningZh": "大楼、账单",
    "review": "OK",
    "source_file": "tup_n4\\files\\n4_07215_ビル_大楼、账单.png",
    "site_image": "assets/images/n4_07215_ビル.png"
  },
  {
    "id": "n4_07237",
    "word": "中学校",
    "reading": "ちゅうがっこう",
    "meaning": "junior high school,middle school",
    "meaningZh": "初中、中学",
    "review": "OK",
    "source_file": "tup_n4\\files\\n4_07237_中学校_初中、中学.png",
    "site_image": "assets/images/n4_07237_中学校.png"
  },
  {
    "id": "n4_07245",
    "word": "事務所",
    "reading": "じむしょ",
    "meaning": "office",
    "meaningZh": "办公室、事务所",
    "review": "OK",
    "source_file": "tup_n4\\files\\n4_07245_事務所_办公室、事务所.png",
    "site_image": "assets/images/n4_07245_事務所.png"
  },
  {
    "id": "n4_07261",
    "word": "会場",
    "reading": "かいじょう",
    "meaning": "assembly hall or meeting place",
    "meaningZh": "会场、集合地点",
    "review": "OK",
    "source_file": "tup_n4\\files\\n4_07261_会場_会场、集合地点.png",
    "site_image": "assets/images/n4_07261_会場.png"
  },
  {
    "id": "n4_07322",
    "word": "地震",
    "reading": "じしん",
    "meaning": "earthquake",
    "meaningZh": "地震",
    "review": "OK",
    "source_file": "tup_n4\\files\\n4_07322_地震_地震.png",
    "site_image": "assets/images/n4_07322_地震.png"
  },
  {
    "id": "n4_07340",
    "word": "大学生",
    "reading": "だいがくせい",
    "meaning": "university student",
    "meaningZh": "大学生",
    "review": "OK",
    "source_file": "tup_n4\\files\\n4_07340_大学生_大学生.png",
    "site_image": "assets/images/n4_07340_大学生.png"
  },
  {
    "id": "n4_07341",
    "word": "天気予報",
    "reading": "てんきよほう",
    "meaning": "weather forecast",
    "meaningZh": "天气预报",
    "review": "OK",
    "source_file": "tup_n4\\files\\n4_07341_天気予報_天气预报.png",
    "site_image": "assets/images/n4_07341_天気予報.png"
  },
  {
    "id": "n4_07342",
    "word": "太る",
    "reading": "ふとる",
    "meaning": "to become fat",
    "meaningZh": "变胖",
    "review": "OK",
    "source_file": "tup_n4\\files\\n4_07342_太る_变胖.png",
    "site_image": "assets/images/n4_07342_太る.png"
  },
  {
    "id": "n4_07362",
    "word": "小学校",
    "reading": "しょうがっこう",
    "meaning": "elementary school",
    "meaningZh": "小学",
    "review": "OK",
    "source_file": "tup_n4\\files\\n4_07362_小学校_小学.png",
    "site_image": "assets/images/n4_07362_小学校.png"
  },
  {
    "id": "n4_07369",
    "word": "工場",
    "reading": "こうじょう",
    "meaning": "factory",
    "meaningZh": "工厂",
    "review": "OK",
    "source_file": "tup_n4\\files\\n4_07369_工場_工厂.png",
    "site_image": "assets/images/n4_07369_工場.png"
  },
  {
    "id": "n4_07377",
    "word": "店員",
    "reading": "てんいん",
    "meaning": "shop assistant",
    "meaningZh": "店员",
    "review": "OK",
    "source_file": "tup_n4\\files\\n4_07377_店員_店员.png",
    "site_image": "assets/images/n4_07377_店員.png"
  },
  {
    "id": "n4_07420",
    "word": "拾う",
    "reading": "ひろう",
    "meaning": "to pick up,to gather",
    "meaningZh": "捡起、收集",
    "review": "OK",
    "source_file": "tup_n4\\files\\n4_07420_拾う_捡起、收集.png",
    "site_image": "assets/images/n4_07420_拾う.png"
  },
  {
    "id": "n4_07438",
    "word": "新聞社",
    "reading": "しんぶんしゃ",
    "meaning": "newspaper company",
    "meaningZh": "报社",
    "review": "OK",
    "source_file": "tup_n4\\files\\n4_07438_新聞社_报社.png",
    "site_image": "assets/images/n4_07438_新聞社.png"
  },
  {
    "id": "n4_07439",
    "word": "旅館",
    "reading": "りょかん",
    "meaning": "Japanese hotel",
    "meaningZh": "日式旅馆",
    "review": "OK",
    "source_file": "tup_n4\\files\\n4_07439_旅館_日式旅馆.png",
    "site_image": "assets/images/n4_07439_旅館.png"
  },
  {
    "id": "n4_07444",
    "word": "星",
    "reading": "ほし",
    "meaning": "star",
    "meaningZh": "星星",
    "review": "OK",
    "source_file": "tup_n4\\files\\n4_07444_星_星星.png",
    "site_image": "assets/images/n4_07444_星.png"
  },
  {
    "id": "n4_07486",
    "word": "汽車",
    "reading": "きしゃ",
    "meaning": "steam train",
    "meaningZh": "蒸汽火车",
    "review": "OK",
    "source_file": "tup_n4\\files\\n4_07486_汽車_蒸汽火车.png",
    "site_image": "assets/images/n4_07486_汽車.png"
  },
  {
    "id": "n4_07504",
    "word": "湯",
    "reading": "ゆ",
    "meaning": "hot water",
    "meaningZh": "热水",
    "review": "OK",
    "source_file": "tup_n4\\files\\n4_07504_湯_热水.png",
    "site_image": "assets/images/n4_07504_湯.png"
  },
  {
    "id": "n4_07509",
    "word": "火",
    "reading": "ひ",
    "meaning": "fire",
    "meaningZh": "火、火灾",
    "review": "OK",
    "source_file": "tup_n4\\files\\n4_07509_火_火、火灾.png",
    "site_image": "assets/images/n4_07509_火.png"
  },
  {
    "id": "n4_07510",
    "word": "火事",
    "reading": "かじ",
    "meaning": "fire",
    "meaningZh": "火、火灾",
    "review": "OK",
    "source_file": "tup_n4\\files\\n4_07510_火事_火、火灾.png",
    "site_image": "assets/images/n4_07510_火事.png"
  },
  {
    "id": "n4_07516",
    "word": "焼ける",
    "reading": "やける",
    "meaning": "to burn,to be roasted",
    "meaningZh": "燃烧、烤焦",
    "review": "OK",
    "source_file": "tup_n4\\files\\n4_07516_焼ける_燃烧、烤焦.png",
    "site_image": "assets/images/n4_07516_焼ける.png"
  },
  {
    "id": "n4_07521",
    "word": "特急",
    "reading": "とっきゅう",
    "meaning": "limited express train (faster than an express train)",
    "meaningZh": "特急列车",
    "review": "OK",
    "source_file": "tup_n4\\files\\n4_07521_特急_特急列车.png",
    "site_image": "assets/images/n4_07521_特急.png"
  },
  {
    "id": "n4_07549",
    "word": "眠る",
    "reading": "ねむる",
    "meaning": "to sleep",
    "meaningZh": "睡觉",
    "review": "OK",
    "source_file": "tup_n4\\files\\n4_07549_眠る_睡觉.png",
    "site_image": "assets/images/n4_07549_眠る.png"
  },
  {
    "id": "n4_07555",
    "word": "研究室",
    "reading": "けんきゅうしつ",
    "meaning": "study room,laboratory",
    "meaningZh": "研究室、实验室",
    "review": "OK",
    "source_file": "tup_n4\\files\\n4_07555_研究室_研究室、实验室.png",
    "site_image": "assets/images/n4_07555_研究室.png"
  },
  {
    "id": "n4_07567",
    "word": "空港",
    "reading": "くうこう",
    "meaning": "airport",
    "meaningZh": "机场",
    "review": "OK",
    "source_file": "tup_n4\\files\\n4_07567_空港_机场.png",
    "site_image": "assets/images/n4_07567_空港.png"
  },
  {
    "id": "n4_07573",
    "word": "米",
    "reading": "こめ",
    "meaning": "uncooked rice",
    "meaningZh": "米、生米",
    "review": "OK",
    "source_file": "tup_n4\\files\\n4_07573_米_米、生米.png",
    "site_image": "assets/images/n4_07573_米.png"
  },
  {
    "id": "n4_07592",
    "word": "背中",
    "reading": "せなか",
    "meaning": "back of the body",
    "meaningZh": "背部、后背",
    "review": "OK",
    "source_file": "tup_n4\\files\\n4_07592_背中_背部、后背.png",
    "site_image": "assets/images/n4_07592_背中.png"
  },
  {
    "id": "n4_07597",
    "word": "舟",
    "reading": "ふね",
    "meaning": "ship",
    "meaningZh": "船",
    "review": "OK",
    "source_file": "tup_n4\\files\\n4_07597_舟_船.png",
    "site_image": "assets/images/n4_07597_舟.png"
  },
  {
    "id": "n4_07604",
    "word": "虫",
    "reading": "むし",
    "meaning": "insect",
    "meaningZh": "虫、昆虫",
    "review": "OK",
    "source_file": "tup_n4\\files\\n4_07604_虫_虫、昆虫.png",
    "site_image": "assets/images/n4_07604_虫.png"
  },
  {
    "id": "n4_07640",
    "word": "踊る",
    "reading": "おどる",
    "meaning": "to dance",
    "meaningZh": "跳舞",
    "review": "OK",
    "source_file": "tup_n4\\files\\n4_07640_踊る_跳舞.png",
    "site_image": "assets/images/n4_07640_踊る.png"
  },
  {
    "id": "n4_07662",
    "word": "運転",
    "reading": "うんてん・する",
    "meaning": "to drive",
    "meaningZh": "驾驶",
    "review": "OK",
    "source_file": "tup_n4\\files\\n4_07662_運転_驾驶.png",
    "site_image": "assets/images/n4_07662_運転.png"
  },
  {
    "id": "n4_07674",
    "word": "釣る",
    "reading": "つる",
    "meaning": "to fish",
    "meaningZh": "钓鱼",
    "review": "OK",
    "source_file": "tup_n4\\files\\n4_07674_釣る_钓鱼.png",
    "site_image": "assets/images/n4_07674_釣る.png"
  },
  {
    "id": "n4_07685",
    "word": "雲",
    "reading": "くも",
    "meaning": "cloud",
    "meaningZh": "云",
    "review": "OK",
    "source_file": "tup_n4\\files\\n4_07685_雲_云.png",
    "site_image": "assets/images/n4_07685_雲.png"
  },
  {
    "id": "n4_07691",
    "word": "食事",
    "reading": "しょくじ・する",
    "meaning": "to have a meal",
    "meaningZh": "吃饭、用餐",
    "review": "OK",
    "source_file": "tup_n4\\files\\n4_07691_食事_吃饭、用餐.png",
    "site_image": "assets/images/n4_07691_食事.png"
  },
  {
    "id": "n4_07698",
    "word": "高校",
    "reading": "こうこう",
    "meaning": "high school",
    "meaningZh": "高中",
    "review": "OK",
    "source_file": "tup_n4\\files\\n4_07698_高校_高中.png",
    "site_image": "assets/images/n4_07698_高校.png"
  },
  {
    "id": "n4_07699",
    "word": "高校生",
    "reading": "こうこうせい",
    "meaning": "high school student",
    "meaningZh": "高中生",
    "review": "OK",
    "source_file": "tup_n4\\files\\n4_07699_高校生_高中生.png",
    "site_image": "assets/images/n4_07699_高校生.png"
  },
  {
    "id": "n4_07700",
    "word": "高等学校",
    "reading": "こうとうがっこう",
    "meaning": "high school",
    "meaningZh": "高中",
    "review": "OK",
    "source_file": "tup_n4\\files\\n4_07700_高等学校_高中.png",
    "site_image": "assets/images/n4_07700_高等学校.png"
  },
  {
    "id": "n5_07718",
    "word": "いす",
    "reading": "いす / イス",
    "meaning": "chair",
    "meaningZh": "椅子",
    "review": "OK",
    "source_file": "tup\\n5_07718_いす_00001_.png",
    "site_image": "assets/images/n5_07718_いす.png"
  },
  {
    "id": "n5_07725",
    "word": "おなか",
    "reading": "おなか",
    "meaning": "stomach",
    "meaningZh": "肚子、胃",
    "review": "OK",
    "source_file": "tup\\n5_07725_おなか_00000.png",
    "site_image": "assets/images/n5_07725_おなか.png"
  },
  {
    "id": "n5_07726",
    "word": "おばあさん",
    "reading": "おばあさん / おばーさん",
    "meaning": "grandmother,female senior-citizen",
    "meaningZh": "祖母、老奶奶",
    "review": "OK",
    "source_file": "tup\\n5_07726_おばあさん_00003_.png",
    "site_image": "assets/images/n5_07726_おばあさん.png"
  },
  {
    "id": "n5_07729",
    "word": "お兄さん",
    "reading": "おにいさん",
    "meaning": "(honorable) older brother",
    "meaningZh": "哥哥",
    "review": "OK",
    "source_file": "tup\\n5_07729＿お兄さん_00000.png",
    "site_image": "assets/images/n5_07729_お兄さん.png"
  },
  {
    "id": "n5_07730",
    "word": "お姉さん",
    "reading": "おねえさん",
    "meaning": "(honorable) older sister",
    "meaningZh": "姐姐",
    "review": "OK",
    "source_file": "tup\\n5_07730_お姉さん.png",
    "site_image": "assets/images/n5_07730_お姉さん.png"
  },
  {
    "id": "n5_07734",
    "word": "お父さん",
    "reading": "おとうさん",
    "meaning": "(honorable) father",
    "meaningZh": "父亲、爸爸",
    "review": "OK",
    "source_file": "tup\\n5_07734＿お父さん_00000.png",
    "site_image": "assets/images/n5_07734_お父さん.png"
  },
  {
    "id": "n5_07736",
    "word": "お茶",
    "reading": "おちゃ",
    "meaning": "green tea",
    "meaningZh": "绿茶",
    "review": "OK",
    "source_file": "tup\\n5_07736_お茶_00001_.png",
    "site_image": "assets/images/n5_07736_お茶.png"
  },
  {
    "id": "n5_07739",
    "word": "お金",
    "reading": "おかね",
    "meaning": "money",
    "meaningZh": "钱",
    "review": "OK",
    "source_file": "tup\\n5_07739_お金.png",
    "site_image": "assets/images/n5_07739_お金.png"
  },
  {
    "id": "n5_07742",
    "word": "かぎ",
    "reading": "かぎ / カギ",
    "meaning": "key",
    "meaningZh": "钥匙",
    "review": "OK",
    "source_file": "tup\\n5_07742_かぎ_00003_.png",
    "site_image": "assets/images/n5_07742_かぎ.png"
  },
  {
    "id": "n5_07744",
    "word": "かばん",
    "reading": "かばん",
    "meaning": "bag,basket",
    "meaningZh": "包、篮子",
    "review": "OK",
    "source_file": "tup\\n5_07744_かばん_00001_.png",
    "site_image": "assets/images/n5_07744_かばん.png"
  },
  {
    "id": "n5_07777",
    "word": "ちゃわん",
    "reading": "ちゃわん",
    "meaning": "rice bowl",
    "meaningZh": "饭碗",
    "review": "OK",
    "source_file": "tup\\n5_07777_ちゃわん_00003_.png",
    "site_image": "assets/images/n5_07777_ちゃわん.png"
  },
  {
    "id": "n5_07786",
    "word": "とり肉",
    "reading": "とりにく",
    "meaning": "chicken meat",
    "meaningZh": "鸡肉",
    "review": "OK",
    "source_file": "tup\\n5_07786_とり肉_00001_.png",
    "site_image": "assets/images/n5_07786_とり肉.png"
  },
  {
    "id": "n5_07821",
    "word": "カップ",
    "reading": "カップ",
    "meaning": "cup",
    "meaningZh": "杯子",
    "review": "OK",
    "source_file": "tup\\n5_07821_カップ_00001_.png",
    "site_image": "assets/images/n5_07821_カップ.png"
  },
  {
    "id": "n5_07822",
    "word": "カメラ",
    "reading": "カメラ / キャメラ",
    "meaning": "camera",
    "meaningZh": "相机",
    "review": "OK",
    "source_file": "tup\\n5_07822_カメラ_00001_.png",
    "site_image": "assets/images/n5_07822_カメラ.png"
  },
  {
    "id": "n5_07830",
    "word": "コップ",
    "reading": "コップ / コツフ",
    "meaning": "a glass",
    "meaningZh": "玻璃杯",
    "review": "OK",
    "source_file": "tup\\n5_07830_コップ.png",
    "site_image": "assets/images/n5_07830_コップ.png"
  },
  {
    "id": "n5_07832",
    "word": "コート",
    "reading": "コート",
    "meaning": "coat,tennis court",
    "meaningZh": "外套、网球场",
    "review": "OK",
    "source_file": "tup\\n5_07832_コート.png",
    "site_image": "assets/images/n5_07832_コート.png"
  },
  {
    "id": "n5_07833",
    "word": "コーヒー",
    "reading": "コーヒー",
    "meaning": "coffee",
    "meaningZh": "咖啡",
    "review": "OK",
    "source_file": "tup\\n5_07833_コーヒー.png",
    "site_image": "assets/images/n5_07833_コーヒー.png"
  },
  {
    "id": "n5_07834",
    "word": "シャツ",
    "reading": "シャツ",
    "meaning": "shirt",
    "meaningZh": "衬衫",
    "review": "OK",
    "source_file": "tup\\n5_07834＿シャツ.png",
    "site_image": "assets/images/n5_07834_シャツ.png"
  },
  {
    "id": "n5_07836",
    "word": "スカート",
    "reading": "スカート",
    "meaning": "skirt",
    "meaningZh": "裙子",
    "review": "OK",
    "source_file": "tup\\n5_07836＿スカート.png",
    "site_image": "assets/images/n5_07836_スカート.png"
  },
  {
    "id": "n5_07838",
    "word": "スプーン",
    "reading": "スプーン / スプン",
    "meaning": "spoon",
    "meaningZh": "勺子",
    "review": "OK",
    "source_file": "tup\\n5_07838_スプーン.png",
    "site_image": "assets/images/n5_07838_スプーン.png"
  },
  {
    "id": "n5_07844",
    "word": "タクシー",
    "reading": "タクシー / タクシ / タキシ",
    "meaning": "taxi",
    "meaningZh": "出租车",
    "review": "OK",
    "source_file": "tup\\n5_07844_タクシー_00001_.png",
    "site_image": "assets/images/n5_07844_タクシー.png"
  },
  {
    "id": "n5_07847",
    "word": "テーブル",
    "reading": "テーブル",
    "meaning": "table",
    "meaningZh": "桌子",
    "review": "OK",
    "source_file": "tup\\n5_07847_テーブル_00001_.png",
    "site_image": "assets/images/n5_07847_テーブル.png"
  },
  {
    "id": "n5_07850",
    "word": "デパート",
    "reading": "デパート",
    "meaning": "department store",
    "meaningZh": "百货商店",
    "review": "OK",
    "source_file": "tup\\n5_07850_デパート_00001_.png",
    "site_image": "assets/images/n5_07850_デパート.png"
  },
  {
    "id": "n5_07853",
    "word": "ナイフ",
    "reading": "ナイフ",
    "meaning": "knife",
    "meaningZh": "刀",
    "review": "OK",
    "source_file": "tup\\n5_07853_ナイフ_00001_.png",
    "site_image": "assets/images/n5_07853_ナイフ.png"
  },
  {
    "id": "n5_07858",
    "word": "バス",
    "reading": "バス",
    "meaning": "bus",
    "meaningZh": "公交车",
    "review": "OK",
    "source_file": "tup\\n5_07858_バス_00001_.png",
    "site_image": "assets/images/n5_07858_バス.png"
  },
  {
    "id": "n5_07860",
    "word": "パン",
    "reading": "パン",
    "meaning": "bread",
    "meaningZh": "面包",
    "review": "OK",
    "source_file": "tup\\n5_07860_パン_00003_.png",
    "site_image": "assets/images/n5_07860_パン.png"
  },
  {
    "id": "n5_07863",
    "word": "フォーク",
    "reading": "フォーク / ホーク",
    "meaning": "fork",
    "meaningZh": "叉子",
    "review": "OK",
    "source_file": "tup\\n5_07863_フォーク_00001_.png",
    "site_image": "assets/images/n5_07863_フォーク.png"
  },
  {
    "id": "n5_07867",
    "word": "ペン",
    "reading": "ペン",
    "meaning": "pen",
    "meaningZh": "笔",
    "review": "OK",
    "source_file": "tup\\n5_07867_ペン_00001_.png",
    "site_image": "assets/images/n5_07867_ペン.png"
  },
  {
    "id": "n5_07869",
    "word": "ホテル",
    "reading": "ホテル",
    "meaning": "hotel",
    "meaningZh": "酒店、旅馆",
    "review": "OK",
    "source_file": "tup\\n5_07869_ホテル_00001_.png",
    "site_image": "assets/images/n5_07869_ホテル.png"
  },
  {
    "id": "n5_07871",
    "word": "ボールペン",
    "reading": "ボールペン / ボール・ペン",
    "meaning": "ball-point pen",
    "meaningZh": "圆珠笔",
    "review": "OK",
    "source_file": "tup\\n5_07871_ボールペン_00001_.png",
    "site_image": "assets/images/n5_07871_ボールペン.png"
  },
  {
    "id": "n5_07879",
    "word": "レストラン",
    "reading": "レストラン",
    "meaning": "restaurant",
    "meaningZh": "餐厅",
    "review": "OK",
    "source_file": "tup\\n5_07879_レストラン_00003_.png",
    "site_image": "assets/images/n5_07879_レストラン.png"
  },
  {
    "id": "n5_07880",
    "word": "ワイシャツ",
    "reading": "ワイシャツ",
    "meaning": "business shirt",
    "meaningZh": "衬衫",
    "review": "OK",
    "source_file": "tup\\n5_07880＿ワイシャツ.png",
    "site_image": "assets/images/n5_07880_ワイシャツ.png"
  },
  {
    "id": "n5_07883",
    "word": "一人",
    "reading": "ひとり",
    "meaning": "one person",
    "meaningZh": "一个人",
    "review": "OK",
    "source_file": "tup\\n5_07883_一人_00001_.png",
    "site_image": "assets/images/n5_07883_一人.png"
  },
  {
    "id": "n5_07893",
    "word": "万年筆",
    "reading": "まんねんひつ",
    "meaning": "fountain pen",
    "meaningZh": "钢笔",
    "review": "OK",
    "source_file": "tup\\n5_07893_万年筆.png",
    "site_image": "assets/images/n5_07893_万年筆.png"
  },
  {
    "id": "n5_07901",
    "word": "上着",
    "reading": "うわぎ",
    "meaning": "jacket",
    "meaningZh": "外套",
    "review": "OK",
    "source_file": "tup\\n5_07901_上着.png",
    "site_image": "assets/images/n5_07901_上着.png"
  },
  {
    "id": "n5_07915",
    "word": "二人",
    "reading": "ふたり",
    "meaning": "two people",
    "meaningZh": "两个人",
    "review": "OK",
    "source_file": "tup\\n5_07915_二人.png",
    "site_image": "assets/images/n5_07915_二人.png"
  },
  {
    "id": "n5_07923",
    "word": "交番",
    "reading": "こうばん",
    "meaning": "police box",
    "meaningZh": "派出所、交番",
    "review": "OK",
    "source_file": "tup\\n5_07923_交番.png",
    "site_image": "assets/images/n5_07923_交番.png"
  },
  {
    "id": "n5_07938",
    "word": "伯父/叔父",
    "reading": "おじいさん",
    "meaning": "grandfather,male senior citizen",
    "meaningZh": "祖父、老爷爷",
    "review": "OK",
    "source_file": "tup\\n5_07938_伯父_叔父_00001_.png",
    "site_image": "assets/images/n5_07938_伯父_叔父.png"
  },
  {
    "id": "n5_07941",
    "word": "体",
    "reading": "からだ",
    "meaning": "body",
    "meaningZh": "身体",
    "review": "OK",
    "source_file": "tup\\n5_07941_体_00003_.png",
    "site_image": "assets/images/n5_07941_体.png"
  },
  {
    "id": "n5_07948",
    "word": "傘",
    "reading": "かさ",
    "meaning": "umbrella",
    "meaningZh": "伞",
    "review": "OK",
    "source_file": "tup\\n5_07948_傘_00001_.png",
    "site_image": "assets/images/n5_07948_傘.png"
  },
  {
    "id": "n5_07950",
    "word": "元気",
    "reading": "げんき",
    "meaning": "health, vitality",
    "meaningZh": "健康、精神",
    "review": "OK",
    "source_file": "tup\\n5_07950_元気_00002_.png",
    "site_image": "assets/images/n5_07950_元気.png"
  },
  {
    "id": "n5_07951",
    "word": "兄",
    "reading": "あに",
    "meaning": "(humble) older brother",
    "meaningZh": "哥哥",
    "review": "OK",
    "source_file": "tup\\n5_07951_兄_00001_.png",
    "site_image": "assets/images/n5_07951_兄.png"
  },
  {
    "id": "n5_07965",
    "word": "公園",
    "reading": "こうえん",
    "meaning": "park",
    "meaningZh": "公园",
    "review": "OK",
    "source_file": "tup\\n5_07965_公園_00001_.png",
    "site_image": "assets/images/n5_07965_公園.png"
  },
  {
    "id": "n5_07975",
    "word": "出る",
    "reading": "でる",
    "meaning": "to appear,to leave",
    "meaningZh": "出现、离开",
    "review": "OK",
    "source_file": "tup\\n5_07975_出る_00001_.png",
    "site_image": "assets/images/n5_07975_出る.png"
  },
  {
    "id": "n5_07980",
    "word": "切符",
    "reading": "きっぷ",
    "meaning": "ticket",
    "meaningZh": "票",
    "review": "OK",
    "source_file": "tup\\n5_07980_切符.png",
    "site_image": "assets/images/n5_07980_切符.png"
  },
  {
    "id": "n5_07985",
    "word": "動物",
    "reading": "どうぶつ",
    "meaning": "animal",
    "meaningZh": "动物",
    "review": "OK",
    "source_file": "tup\\n5_07985_動物_00004_.png",
    "site_image": "assets/images/n5_07985_動物.png"
  },
  {
    "id": "n5_07988",
    "word": "医者",
    "reading": "いしゃ",
    "meaning": "medical doctor",
    "meaningZh": "医生",
    "review": "OK",
    "source_file": "tup\\n5_07988_医者_00001_.png",
    "site_image": "assets/images/n5_07988_医者.png"
  },
  {
    "id": "n5_07998",
    "word": "卵",
    "reading": "たまご",
    "meaning": "egg",
    "meaningZh": "鸡蛋",
    "review": "OK",
    "source_file": "tup\\n5_07998_卵_00001_.png",
    "site_image": "assets/images/n5_07998_卵.png"
  },
  {
    "id": "n5_08001",
    "word": "友達",
    "reading": "ともだち",
    "meaning": "friend",
    "meaningZh": "朋友",
    "review": "OK",
    "source_file": "tup\\n5_08001_友達.png",
    "site_image": "assets/images/n5_08001_友達.png"
  },
  {
    "id": "n5_08003",
    "word": "口",
    "reading": "くち",
    "meaning": "mouth,opening",
    "meaningZh": "嘴、开口",
    "review": "OK",
    "source_file": "tup\\n5_08003_口_00000.png",
    "site_image": "assets/images/n5_08003_口.png"
  },
  {
    "id": "n5_08005",
    "word": "台所",
    "reading": "だいどころ",
    "meaning": "kitchen",
    "meaningZh": "厨房",
    "review": "OK",
    "source_file": "tup\\n5_08005_台所.png",
    "site_image": "assets/images/n5_08005_台所.png"
  },
  {
    "id": "n5_08015",
    "word": "喫茶店",
    "reading": "きっさてん",
    "meaning": "coffee lounge",
    "meaningZh": "咖啡店",
    "review": "OK",
    "source_file": "tup\\n5_08015_喫茶店_00001_.png",
    "site_image": "assets/images/n5_08015_喫茶店.png"
  },
  {
    "id": "n5_08020",
    "word": "図書館",
    "reading": "としょかん",
    "meaning": "library",
    "meaningZh": "图书馆",
    "review": "OK",
    "source_file": "tup\\n5_08020_図書館_00001_.png",
    "site_image": "assets/images/n5_08020_図書館.png"
  },
  {
    "id": "n5_08023",
    "word": "地下鉄",
    "reading": "ちかてつ",
    "meaning": "underground train",
    "meaningZh": "地铁",
    "review": "OK",
    "source_file": "tup\\n5_08023_地下鉄_00003_.png",
    "site_image": "assets/images/n5_08023_地下鉄.png"
  },
  {
    "id": "n5_08024",
    "word": "地図",
    "reading": "ちず",
    "meaning": "map",
    "meaningZh": "地图",
    "review": "OK",
    "source_file": "tup\\n5_08024_地図_00001_.png",
    "site_image": "assets/images/n5_08024_地図.png"
  },
  {
    "id": "n5_08046",
    "word": "天気",
    "reading": "てんき",
    "meaning": "weather",
    "meaningZh": "天气",
    "review": "OK",
    "source_file": "tup\\n5_08046_天気.png",
    "site_image": "assets/images/n5_08046_天気.png"
  },
  {
    "id": "n5_08047",
    "word": "太い",
    "reading": "ふとい",
    "meaning": "fat",
    "meaningZh": "胖的、粗的",
    "review": "OK",
    "source_file": "tup\\n5_08047_太い_00003_.png",
    "site_image": "assets/images/n5_08047_太い.png"
  },
  {
    "id": "n5_08048",
    "word": "奥さん",
    "reading": "おくさん",
    "meaning": "(honorable) wife",
    "meaningZh": "妻子、太太",
    "review": "OK",
    "source_file": "tup\\n5_08048_奥さん.png",
    "site_image": "assets/images/n5_08048_奥さん.png"
  },
  {
    "id": "n5_08050",
    "word": "女の子",
    "reading": "おんなのこ",
    "meaning": "girl",
    "meaningZh": "女孩",
    "review": "OK",
    "source_file": "tup\\n5_08050_女の子_00001_.png",
    "site_image": "assets/images/n5_08050_女の子.png"
  },
  {
    "id": "n5_08052",
    "word": "妹",
    "reading": "いもうと",
    "meaning": "(humble) younger sister",
    "meaningZh": "妹妹",
    "review": "OK",
    "source_file": "tup\\n5_08052_妹_00001_.png",
    "site_image": "assets/images/n5_08052_妹.png"
  },
  {
    "id": "n5_08053",
    "word": "姉",
    "reading": "あね",
    "meaning": "(humble) older sister",
    "meaningZh": "姐姐",
    "review": "OK",
    "source_file": "tup\\n5_08053_姉_00001_.png",
    "site_image": "assets/images/n5_08053_姉.png"
  },
  {
    "id": "n5_08057",
    "word": "子供",
    "reading": "こども",
    "meaning": "child",
    "meaningZh": "孩子",
    "review": "OK",
    "source_file": "tup\\n5_08057_子供_00001_.png",
    "site_image": "assets/images/n5_08057_子供.png"
  },
  {
    "id": "n5_08059",
    "word": "学校",
    "reading": "がっこう",
    "meaning": "school",
    "meaningZh": "学校",
    "review": "OK",
    "source_file": "tup\\n5_08059_学校.png",
    "site_image": "assets/images/n5_08059_学校.png"
  },
  {
    "id": "n5_08060",
    "word": "学生",
    "reading": "がくせい",
    "meaning": "student",
    "meaningZh": "学生",
    "review": "OK",
    "source_file": "tup\\n5_08060_学生.png",
    "site_image": "assets/images/n5_08060_学生.png"
  },
  {
    "id": "n5_08062",
    "word": "家",
    "reading": "いえ",
    "meaning": "house",
    "meaningZh": "家、房子",
    "review": "OK",
    "source_file": "tup\\n5_08062_家_00001_.png",
    "site_image": "assets/images/n5_08062_家.png"
  },
  {
    "id": "n5_08064",
    "word": "家族",
    "reading": "かぞく",
    "meaning": "family",
    "meaningZh": "家人、家庭",
    "review": "OK",
    "source_file": "tup\\n5_08064_家族.png",
    "site_image": "assets/images/n5_08064_家族.png"
  },
  {
    "id": "n5_08075",
    "word": "川/河",
    "reading": "かわ",
    "meaning": "river",
    "meaningZh": "河",
    "review": "OK",
    "source_file": "tup\\n5_08075_川_河_00004_.png",
    "site_image": "assets/images/n5_08075_川_河.png"
  },
  {
    "id": "n5_08079",
    "word": "帽子",
    "reading": "ぼうし",
    "meaning": "hat",
    "meaningZh": "帽子",
    "review": "OK",
    "source_file": "tup\\n5_08079_帽子.png",
    "site_image": "assets/images/n5_08079_帽子.png"
  },
  {
    "id": "n5_08082",
    "word": "店",
    "reading": "みせ",
    "meaning": "shop",
    "meaningZh": "商店",
    "review": "OK",
    "source_file": "tup\\n5_08082_店.png",
    "site_image": "assets/images/n5_08082_店.png"
  },
  {
    "id": "n5_08083",
    "word": "座る",
    "reading": "すわる",
    "meaning": "to sit",
    "meaningZh": "坐",
    "review": "OK",
    "source_file": "tup\\n5_08083_座る_00004_.png",
    "site_image": "assets/images/n5_08083_座る.png"
  },
  {
    "id": "n5_08086",
    "word": "建物",
    "reading": "たてもの",
    "meaning": "building",
    "meaningZh": "建筑物",
    "review": "OK",
    "source_file": "tup\\n5_08086_建物_00004_.png",
    "site_image": "assets/images/n5_08086_建物.png"
  },
  {
    "id": "n5_08088",
    "word": "弟",
    "reading": "おとうと",
    "meaning": "younger brother",
    "meaningZh": "弟弟",
    "review": "OK",
    "source_file": "tup\\n5_08088_弟_00001_.png",
    "site_image": "assets/images/n5_08088_弟.png"
  },
  {
    "id": "n5_08095",
    "word": "御飯",
    "reading": "ごはん",
    "meaning": "cooked rice,meal",
    "meaningZh": "米饭、饭",
    "review": "OK",
    "source_file": "tup\\n5_08095_御飯_00001_.png",
    "site_image": "assets/images/n5_08095_御飯.png"
  },
  {
    "id": "n5_08102",
    "word": "手",
    "reading": "て",
    "meaning": "hand",
    "meaningZh": "手",
    "review": "OK",
    "source_file": "tup\\n5_08102_手_00002_.png",
    "site_image": "assets/images/n5_08102_手.png"
  },
  {
    "id": "n5_08103",
    "word": "手紙",
    "reading": "てがみ",
    "meaning": "letter",
    "meaningZh": "信",
    "review": "OK",
    "source_file": "tup\\n5_08103_手紙.png",
    "site_image": "assets/images/n5_08103_手紙.png"
  },
  {
    "id": "n5_08106",
    "word": "掃除",
    "reading": "そうじする",
    "meaning": "to clean, to sweep",
    "meaningZh": "打扫",
    "review": "OK",
    "source_file": "tup\\n5_08106_掃除_00001_.png",
    "site_image": "assets/images/n5_08106_掃除.png"
  },
  {
    "id": "n5_08115",
    "word": "新聞",
    "reading": "しんぶん",
    "meaning": "newspaper",
    "meaningZh": "报纸",
    "review": "OK",
    "source_file": "tup\\n5_08115_新聞_00001_.png",
    "site_image": "assets/images/n5_08115_新聞.png"
  },
  {
    "id": "n5_08129",
    "word": "昼御飯",
    "reading": "ひるごはん",
    "meaning": "midday meal",
    "meaningZh": "午饭",
    "review": "OK",
    "source_file": "tup\\n5_08129_昼御飯.png",
    "site_image": "assets/images/n5_08129_昼御飯.png"
  },
  {
    "id": "n5_08131",
    "word": "時計",
    "reading": "とけい",
    "meaning": "watch,clock",
    "meaningZh": "手表、钟",
    "review": "OK",
    "source_file": "tup\\n5_08131_時計_00001_.png",
    "site_image": "assets/images/n5_08131_時計.png"
  },
  {
    "id": "n5_08134",
    "word": "晩御飯",
    "reading": "ばんごはん",
    "meaning": "evening meal",
    "meaningZh": "晚饭",
    "review": "OK",
    "source_file": "tup\\n5_08134_晩御飯_00003_.png",
    "site_image": "assets/images/n5_08134_晩御飯.png"
  },
  {
    "id": "n5_08141",
    "word": "曇り",
    "reading": "くもり",
    "meaning": "cloudy weather",
    "meaningZh": "阴天",
    "review": "OK",
    "source_file": "tup\\n5_08141_曇り.png",
    "site_image": "assets/images/n5_08141_曇り.png"
  },
  {
    "id": "n5_08150",
    "word": "木",
    "reading": "き",
    "meaning": "tree,wood",
    "meaningZh": "树、木头",
    "review": "OK",
    "source_file": "tup\\n5_08150_木_00001_.png",
    "site_image": "assets/images/n5_08150_木.png"
  },
  {
    "id": "n5_08152",
    "word": "本",
    "reading": "ほん",
    "meaning": "book",
    "meaningZh": "书",
    "review": "OK",
    "source_file": "tup\\n5_08152_本_00001_.png",
    "site_image": "assets/images/n5_08152_本.png"
  },
  {
    "id": "n5_08154",
    "word": "机",
    "reading": "つくえ",
    "meaning": "desk",
    "meaningZh": "桌子、书桌",
    "review": "OK",
    "source_file": "tup\\n5_08154_机.png",
    "site_image": "assets/images/n5_08154_机.png"
  },
  {
    "id": "n5_08161",
    "word": "果物",
    "reading": "くだもの",
    "meaning": "fruit",
    "meaningZh": "水果",
    "review": "OK",
    "source_file": "tup\\n5_08161_果物_00001_.png",
    "site_image": "assets/images/n5_08161_果物.png"
  },
  {
    "id": "n5_08170",
    "word": "歩く",
    "reading": "あるく",
    "meaning": "to walk",
    "meaningZh": "走路",
    "review": "OK",
    "source_file": "tup\\n5_08170_歩く_00001_.png",
    "site_image": "assets/images/n5_08170_歩く.png"
  },
  {
    "id": "n5_08171",
    "word": "歯",
    "reading": "は",
    "meaning": "tooth",
    "meaningZh": "牙齿",
    "review": "OK",
    "source_file": "tup\\n5_08171_歯.png",
    "site_image": "assets/images/n5_08171_歯.png"
  },
  {
    "id": "n5_08179",
    "word": "水",
    "reading": "みず",
    "meaning": "water",
    "meaningZh": "水",
    "review": "OK",
    "source_file": "tup\\n5_08179_水_00003_.png",
    "site_image": "assets/images/n5_08179_水.png"
  },
  {
    "id": "n5_08184",
    "word": "洋服",
    "reading": "ようふく",
    "meaning": "western-style clothes",
    "meaningZh": "西式衣服",
    "review": "OK",
    "source_file": "tup\\n5_08184_洋服.png",
    "site_image": "assets/images/n5_08184_洋服.png"
  },
  {
    "id": "n5_08187",
    "word": "海",
    "reading": "うみ",
    "meaning": "sea",
    "meaningZh": "海",
    "review": "OK",
    "source_file": "tup\\n5_08187_海.png",
    "site_image": "assets/images/n5_08187_海.png"
  },
  {
    "id": "n5_08200",
    "word": "牛乳",
    "reading": "ぎゅうにゅう",
    "meaning": "milk",
    "meaningZh": "牛奶",
    "review": "OK",
    "source_file": "tup\\n5_08200_牛乳_00003_.png",
    "site_image": "assets/images/n5_08200_牛乳.png"
  },
  {
    "id": "n5_08203",
    "word": "犬",
    "reading": "いぬ",
    "meaning": "dog",
    "meaningZh": "狗",
    "review": "OK",
    "source_file": "tup\\n5_08203_犬_00000.png",
    "site_image": "assets/images/n5_08203_犬.png"
  },
  {
    "id": "n5_08205",
    "word": "猫",
    "reading": "ねこ",
    "meaning": "cat",
    "meaningZh": "猫",
    "review": "OK",
    "source_file": "tup\\n5_08205_猫_00000.png",
    "site_image": "assets/images/n5_08205_猫.png"
  },
  {
    "id": "n5_08211",
    "word": "男の子",
    "reading": "おとこのこ",
    "meaning": "boy",
    "meaningZh": "男孩",
    "review": "OK",
    "source_file": "tup\\n5_08211_男の子_00003_.png",
    "site_image": "assets/images/n5_08211_男の子.png"
  },
  {
    "id": "n5_08213",
    "word": "留学生",
    "reading": "りゅうがくせい",
    "meaning": "overseas student",
    "meaningZh": "留学生",
    "review": "OK",
    "source_file": "tup\\n5_08213_留学生.png",
    "site_image": "assets/images/n5_08213_留学生.png"
  },
  {
    "id": "n5_08217",
    "word": "病院",
    "reading": "びょういん",
    "meaning": "hospital",
    "meaningZh": "医院",
    "review": "OK",
    "source_file": "tup\\n5_08217_病院_00001_.png",
    "site_image": "assets/images/n5_08217_病院.png"
  },
  {
    "id": "n5_08224",
    "word": "目",
    "reading": "め",
    "meaning": "eye",
    "meaningZh": "眼睛",
    "review": "OK",
    "source_file": "tup\\n5_08224_目_00004_.png",
    "site_image": "assets/images/n5_08224_目.png"
  },
  {
    "id": "n5_08230",
    "word": "砂糖",
    "reading": "さとう",
    "meaning": "sugar",
    "meaningZh": "糖",
    "review": "OK",
    "source_file": "tup\\n5_08230_砂糖_00003_.png",
    "site_image": "assets/images/n5_08230_砂糖.png"
  },
  {
    "id": "n5_08236",
    "word": "立つ",
    "reading": "たつ",
    "meaning": "to stand",
    "meaningZh": "站",
    "review": "OK",
    "source_file": "tup\\n5_08236_立つ_00004_.png",
    "site_image": "assets/images/n5_08236_立つ.png"
  },
  {
    "id": "n5_08238",
    "word": "箱",
    "reading": "はこ",
    "meaning": "box",
    "meaningZh": "箱子、盒子",
    "review": "OK",
    "source_file": "tup\\n5_08238_箱_00001_.png",
    "site_image": "assets/images/n5_08238_箱.png"
  },
  {
    "id": "n5_08239",
    "word": "紅茶",
    "reading": "こうちゃ",
    "meaning": "black tea",
    "meaningZh": "红茶",
    "review": "OK",
    "source_file": "tup\\n5_08239_紅茶_00001_.png",
    "site_image": "assets/images/n5_08239_紅茶.png"
  },
  {
    "id": "n5_08240",
    "word": "紙",
    "reading": "かみ",
    "meaning": "paper",
    "meaningZh": "纸",
    "review": "OK",
    "source_file": "tup\\n5_08240_紙_00001_.png",
    "site_image": "assets/images/n5_08240_紙.png"
  },
  {
    "id": "n5_08251",
    "word": "耳",
    "reading": "みみ",
    "meaning": "ear",
    "meaningZh": "耳朵",
    "review": "OK",
    "source_file": "tup\\n5_08251_耳_00000.png",
    "site_image": "assets/images/n5_08251_耳.png"
  },
  {
    "id": "n5_08253",
    "word": "肉",
    "reading": "にく",
    "meaning": "meat",
    "meaningZh": "肉",
    "review": "OK",
    "source_file": "tup\\n5_08253_肉_00001_.png",
    "site_image": "assets/images/n5_08253_肉.png"
  },
  {
    "id": "n5_08259",
    "word": "自転車",
    "reading": "じてんしゃ",
    "meaning": "bicycle",
    "meaningZh": "自行车",
    "review": "OK",
    "source_file": "tup\\n5_08259_自転車_00001_.png",
    "site_image": "assets/images/n5_08259_自転車.png"
  },
  {
    "id": "n5_08261",
    "word": "花",
    "reading": "はな",
    "meaning": "flower",
    "meaningZh": "花",
    "review": "OK",
    "source_file": "tup\\n5_08261_花_00001_.png",
    "site_image": "assets/images/n5_08261_花.png"
  },
  {
    "id": "n5_08262",
    "word": "花瓶",
    "reading": "かびん",
    "meaning": "a vase",
    "meaningZh": "花瓶",
    "review": "OK",
    "source_file": "tup\\n5_08262_花瓶_00001_.png",
    "site_image": "assets/images/n5_08262_花瓶.png"
  },
  {
    "id": "n5_08267",
    "word": "葉書",
    "reading": "はがき",
    "meaning": "postcard",
    "meaningZh": "明信片",
    "review": "OK",
    "source_file": "tup\\n5_08267_葉書.png",
    "site_image": "assets/images/n5_08267_葉書.png"
  },
  {
    "id": "n5_08269",
    "word": "薬",
    "reading": "くすり",
    "meaning": "medicine",
    "meaningZh": "药",
    "review": "OK",
    "source_file": "tup\\n5_08269_薬_00003_.png",
    "site_image": "assets/images/n5_08269_薬.png"
  },
  {
    "id": "n5_08282",
    "word": "読む",
    "reading": "よむ",
    "meaning": "to read",
    "meaningZh": "读",
    "review": "OK",
    "source_file": "tup\\n5_08282_読む_00003_.png",
    "site_image": "assets/images/n5_08282_読む.png"
  },
  {
    "id": "n5_08295",
    "word": "走る",
    "reading": "はしる",
    "meaning": "to run",
    "meaningZh": "跑",
    "review": "OK",
    "source_file": "tup\\n5_08295_走る_00003_.png",
    "site_image": "assets/images/n5_08295_走る.png"
  },
  {
    "id": "n5_08297",
    "word": "足",
    "reading": "あし",
    "meaning": "foot,leg",
    "meaningZh": "脚、腿",
    "review": "OK",
    "source_file": "tup\\n5_08297_足.png",
    "site_image": "assets/images/n5_08297_足.png"
  },
  {
    "id": "n5_08298",
    "word": "車",
    "reading": "くるま",
    "meaning": "car,vehicle",
    "meaningZh": "车、车辆",
    "review": "OK",
    "source_file": "tup\\n5_08298_車_00001_.png",
    "site_image": "assets/images/n5_08298_車.png"
  },
  {
    "id": "n5_08309",
    "word": "道",
    "reading": "みち",
    "meaning": "street",
    "meaningZh": "道路、街道",
    "review": "OK",
    "source_file": "tup\\n5_08309_道.png",
    "site_image": "assets/images/n5_08309_道.png"
  },
  {
    "id": "n5_08312",
    "word": "部屋",
    "reading": "へや",
    "meaning": "room",
    "meaningZh": "房间",
    "review": "OK",
    "source_file": "tup\\n5_08312_部屋.png",
    "site_image": "assets/images/n5_08312_部屋.png"
  },
  {
    "id": "n5_08313",
    "word": "郵便局",
    "reading": "ゆうびんきょく",
    "meaning": "post office",
    "meaningZh": "邮局",
    "review": "OK",
    "source_file": "tup\\n5_08313_郵便局_00001_.png",
    "site_image": "assets/images/n5_08313_郵便局.png"
  },
  {
    "id": "n5_08314",
    "word": "重い",
    "reading": "おもい",
    "meaning": "heavy",
    "meaningZh": "重的",
    "review": "OK",
    "source_file": "tup\\n5_08314_重い_00001_.png",
    "site_image": "assets/images/n5_08314_重い.png"
  },
  {
    "id": "n5_08315",
    "word": "野菜",
    "reading": "やさい",
    "meaning": "vegetable",
    "meaningZh": "蔬菜",
    "review": "OK",
    "source_file": "tup\\n5_08315_野菜_00001_.png",
    "site_image": "assets/images/n5_08315_野菜.png"
  },
  {
    "id": "n5_08317",
    "word": "鉛筆",
    "reading": "えんぴつ",
    "meaning": "pencil",
    "meaningZh": "铅笔",
    "review": "OK",
    "source_file": "tup\\n5_08317_鉛筆_00001_.png",
    "site_image": "assets/images/n5_08317_鉛筆.png"
  },
  {
    "id": "n5_08318",
    "word": "銀行",
    "reading": "ぎんこう",
    "meaning": "bank",
    "meaningZh": "银行",
    "review": "OK",
    "source_file": "tup\\n5_08318_銀行.png",
    "site_image": "assets/images/n5_08318_銀行.png"
  },
  {
    "id": "n5_08326",
    "word": "降る",
    "reading": "ふる",
    "meaning": "to fall, e.g. rain or snow",
    "meaningZh": "下、降落",
    "review": "OK",
    "source_file": "tup\\n5_08326_降る_00003_.png",
    "site_image": "assets/images/n5_08326_降る.png"
  },
  {
    "id": "n5_08329",
    "word": "雑誌",
    "reading": "ざっし",
    "meaning": "magazine",
    "meaningZh": "杂志",
    "review": "OK",
    "source_file": "tup\\n5_08329_雑誌_00001_.png",
    "site_image": "assets/images/n5_08329_雑誌.png"
  },
  {
    "id": "n5_08331",
    "word": "雨",
    "reading": "あめ",
    "meaning": "rain",
    "meaningZh": "雨",
    "review": "OK",
    "source_file": "tup\\n5_08331_雨.png",
    "site_image": "assets/images/n5_08331_雨.png"
  },
  {
    "id": "n5_08332",
    "word": "雪",
    "reading": "ゆき",
    "meaning": "snow",
    "meaningZh": "雪",
    "review": "OK",
    "source_file": "tup\\n5_08332_雪_00001_.png",
    "site_image": "assets/images/n5_08332_雪.png"
  },
  {
    "id": "n5_08335",
    "word": "電話",
    "reading": "でんわ",
    "meaning": "telephone",
    "meaningZh": "电话",
    "review": "OK",
    "source_file": "tup\\n5_08335_電話.png",
    "site_image": "assets/images/n5_08335_電話.png"
  },
  {
    "id": "n5_08336",
    "word": "電車",
    "reading": "でんしゃ",
    "meaning": "electric train",
    "meaningZh": "电车",
    "review": "OK",
    "source_file": "tup\\n5_08336_電車_00001_.png",
    "site_image": "assets/images/n5_08336_電車.png"
  },
  {
    "id": "n5_08340",
    "word": "靴",
    "reading": "くつ",
    "meaning": "shoes",
    "meaningZh": "鞋",
    "review": "OK",
    "source_file": "tup\\n5_08340_靴.png",
    "site_image": "assets/images/n5_08340_靴.png"
  },
  {
    "id": "n5_08341",
    "word": "靴下",
    "reading": "くつした",
    "meaning": "socks",
    "meaningZh": "袜子",
    "review": "OK",
    "source_file": "tup\\n5_08341_靴下.png",
    "site_image": "assets/images/n5_08341_靴下.png"
  },
  {
    "id": "n5_08350",
    "word": "食べ物",
    "reading": "たべもの",
    "meaning": "food",
    "meaningZh": "食物",
    "review": "OK",
    "source_file": "tup\\n5_08350_食べ物_00004_.png",
    "site_image": "assets/images/n5_08350_食べ物.png"
  },
  {
    "id": "n5_08356",
    "word": "高い",
    "reading": "たかい",
    "meaning": "tall, expensive",
    "meaningZh": "高、高价",
    "review": "OK",
    "source_file": "tup\\n5_08356_高い_00001_.png",
    "site_image": "assets/images/n5_08356_高い.png"
  },
  {
    "id": "n5_08357",
    "word": "魚",
    "reading": "さかな",
    "meaning": "fish",
    "meaningZh": "鱼",
    "review": "OK",
    "source_file": "tup\\n5_08357_魚.png",
    "site_image": "assets/images/n5_08357_魚.png"
  },
  {
    "id": "n5_08358",
    "word": "鳥",
    "reading": "とり",
    "meaning": "bird",
    "meaningZh": "鸟",
    "review": "OK",
    "source_file": "tup\\n5_08358_鳥_00002_.png",
    "site_image": "assets/images/n5_08358_鳥.png"
  },
  {
    "id": "n5_08361",
    "word": "黄色い",
    "reading": "きいろい",
    "meaning": "yellow",
    "meaningZh": "黄色、黄的",
    "review": "OK",
    "source_file": "tup\\n5_08361_黄色い_00001_.png",
    "site_image": "assets/images/n5_08361_黄色い.png"
  },
  {
    "id": "n5_08363",
    "word": "黒い",
    "reading": "くろい",
    "meaning": "black",
    "meaningZh": "黑色、黑的",
    "review": "OK",
    "source_file": "tup\\n5_08363_黒い_00004_.png",
    "site_image": "assets/images/n5_08363_黒い.png"
  },
  {
    "id": "n5_08364",
    "word": "鼻",
    "reading": "はな",
    "meaning": "nose",
    "meaningZh": "鼻子",
    "review": "OK",
    "source_file": "tup\\n5_08364＿鼻_00000.png",
    "site_image": "assets/images/n5_08364_鼻.png"
  }
]